LICENSE
README.md
tracking/__init__.py
tracking/api/__init__.py
tracking/api/courier.py
tracking/api/courier_connection.py
tracking/api/estimated_delivery_date.py
tracking/api/tracking.py
tracking/auth.py
tracking/client.py
tracking/configuration.py
tracking/exceptions.py
tracking/models/__init__.py
tracking/models/additional_fields.py
tracking/models/checkpoint.py
tracking/models/checkpoint_coordinate.py
tracking/models/checkpoint_events.py
tracking/models/checkpoint_events_reason.py
tracking/models/checkpoint_source.py
tracking/models/courier.py
tracking/models/courier_connection.py
tracking/models/courier_connection_response_for_get_courier_connections.py
tracking/models/courier_connection_response_for_get_courier_connections_data.py
tracking/models/courier_connection_response_for_get_courier_connections_data_pagination.py
tracking/models/courier_credentials.py
tracking/models/courier_response.py
tracking/models/courier_response_data.py
tracking/models/create_tracking_request.py
tracking/models/create_tracking_request_customers.py
tracking/models/create_tracking_request_delivery_type.py
tracking/models/create_tracking_request_last_mile.py
tracking/models/create_tracking_request_order_promised_delivery_date.py
tracking/models/create_tracking_response.py
tracking/models/credential_field.py
tracking/models/delete_courier_connections_by_id_response.py
tracking/models/delete_tracking_by_id_response.py
tracking/models/detect_courier_request.py
tracking/models/detect_courier_response.py
tracking/models/detect_courier_response_data.py
tracking/models/estimated_delivery_date_request.py
tracking/models/estimated_delivery_date_request_destination_address.py
tracking/models/estimated_delivery_date_request_estimated_pickup.py
tracking/models/estimated_delivery_date_request_estimated_pickup_order_processing_time.py
tracking/models/estimated_delivery_date_request_origin_address.py
tracking/models/estimated_delivery_date_request_weight.py
aftership_tracking_sdk-9.0.0.dist-info/METADATA
aftership_tracking_sdk-9.0.0.dist-info/WHEEL
aftership_tracking_sdk-9.0.0.dist-info/licenses/LICENSE
aftership_tracking_sdk-9.0.0.dist-info/RECORD
