Metadata-Version: 2.4
Name: aftership-tracking-sdk
Version: 9.0.0
Summary: The official AfterShip Tracking Python API library
License: MIT
License-File: LICENSE
Keywords: aftership,tracking,dhl
Author: AfterShip
Author-email: support@aftership.com
Requires-Python: >=3.8
Classifier: Development Status :: 5 - Production/Stable
Classifier: Intended Audience :: Developers
Classifier: License :: OSI Approved :: MIT License
Classifier: Programming Language :: Python :: 3
Classifier: Programming Language :: Python :: 3.8
Classifier: Programming Language :: Python :: 3.9
Classifier: Programming Language :: Python :: 3.10
Classifier: Programming Language :: Python :: 3.11
Classifier: Programming Language :: Python :: 3.12
Classifier: Programming Language :: Python :: 3.13
Classifier: Programming Language :: Python :: 3.14
Classifier: Topic :: Software Development
Requires-Dist: h11 (>=0.16.0)
Requires-Dist: httpx (>=0.28.0)
Requires-Dist: pycryptodome (>=3.9.0)
Requires-Dist: pydantic (>=2)
Requires-Dist: retrying (>=1.3.4,<2.0.0)
Requires-Dist: socksio (>=1.0.0,<2.0.0)
Requires-Dist: typing_extensions (>=4.7.1)
Requires-Dist: urllib3 (>=2.2.2,<3.0.0)
